xai4mri/__init__.py
xai4mri/utils.py
xai4mri/dataloader/__init__.py
xai4mri/dataloader/_temp_implementation.py
xai4mri/dataloader/datasets.py
xai4mri/dataloader/mri_dataloader.py
xai4mri/dataloader/mri_registration.py
xai4mri/dataloader/prune_image.py
xai4mri/dataloader/transformation.py
xai4mri/model/__init__.py
xai4mri/model/interpreter.py
xai4mri/model/mrinets.py
xai4mri/model/transfer.py
xai4mri/visualizer/__init__.py
xai4mri/visualizer/visualize_heatmap.py
xai4mri/visualizer/visualize_mri.py
xai4mri-0.0.1.dist-info/LICENSE
xai4mri-0.0.1.dist-info/METADATA
xai4mri-0.0.1.dist-info/WHEEL
xai4mri-0.0.1.dist-info/top_level.txt
xai4mri-0.0.1.dist-info/RECORD
